thinkagain/__init__.py
thinkagain/core/__init__.py
thinkagain/core/compiled_graph.py
thinkagain/core/constants.py
thinkagain/core/context.py
thinkagain/core/executable.py
thinkagain/core/graph.py
thinkagain/core/graph_executor.py
thinkagain/core/graph_flattener.py
thinkagain/core/parallel.py
thinkagain/core/runtime.py
thinkagain/core/visualization.py
thinkagain/core/worker.py
thinkagain/serve/README.md
thinkagain/serve/__init__.py
thinkagain/serve/openai/__main__.py
thinkagain/serve/openai/models.py
thinkagain/serve/openai/serve_completion.py
thinkagain-0.1.1.dist-info/METADATA
thinkagain-0.1.1.dist-info/WHEEL
thinkagain-0.1.1.dist-info/licenses/LICENSE
thinkagain-0.1.1.dist-info/RECORD
