Metadata-Version: 2.4
Name: thinkagain
Version: 0.1.1
Summary: Minimal, debuggable agent framework for explicit pipelines and computation graphs.
Project-URL: Homepage, https://github.com/BDHU/thinkagain
Project-URL: Repository, https://github.com/BDHU/thinkagain
Project-URL: Issues, https://github.com/BDHU/thinkagain/issues
Author: ThinkAgain contributors
License: Apache-2.0
License-File: LICENSE
Classifier: Development Status :: 3 - Alpha
Classifier: Intended Audience :: Developers
Classifier: License :: OSI Approved :: Apache Software License
Classifier: Programming Language :: Python :: 3
Classifier: Programming Language :: Python :: 3 :: Only
Classifier: Programming Language :: Python :: 3.9
Classifier: Programming Language :: Python :: 3.10
Classifier: Programming Language :: Python :: 3.11
Classifier: Topic :: Software Development :: Libraries
Classifier: Topic :: Software Development :: Libraries :: Application Frameworks
Requires-Python: >=3.9
Provides-Extra: serve
Requires-Dist: fastapi>=0.104.0; extra == 'serve'
Requires-Dist: jsonschema>=4.18.0; extra == 'serve'
Requires-Dist: pydantic>=2.0.0; extra == 'serve'
Requires-Dist: uvicorn>=0.24.0; extra == 'serve'
Provides-Extra: test
Requires-Dist: pytest>=8.4.2; extra == 'test'
